djangocms_animate_on_scroll/__init__.py
djangocms_animate_on_scroll/apps.py
djangocms_animate_on_scroll/cms_plugins.py
djangocms_animate_on_scroll/consts.py
djangocms_animate_on_scroll/forms.py
djangocms_animate_on_scroll/models.py
djangocms_animate_on_scroll/migrations/0001_initial.py
djangocms_animate_on_scroll/migrations/__init__.py
djangocms_animate_on_scroll/static/djangocms_animate_on_scroll/aos.css
djangocms_animate_on_scroll/static/djangocms_animate_on_scroll/aos.js
djangocms_animate_on_scroll/templates/djangocms_animate_on_scroll/aos_anchor.html
djangocms_animate_on_scroll/templates/djangocms_animate_on_scroll/aos_element.html
djangocms_animate_on_scroll-1.0.1.dist-info/METADATA
djangocms_animate_on_scroll-1.0.1.dist-info/WHEEL
djangocms_animate_on_scroll-1.0.1.dist-info/top_level.txt
djangocms_animate_on_scroll-1.0.1.dist-info/RECORD
