Metadata-Version: 2.1
Name: djangocms-animate-on-scroll
Version: 1.0.1
Summary: Allows you to add the animate on scroll plugin to a cms page
Home-page: https://github.com/mcldev/djangocms-animate-on-scroll
Author: michalsnik, Michael Carder
License: MIT
Platform: UNKNOWN
Classifier: Environment :: Web Environment
Classifier: Intended Audience :: Developers
Classifier: License :: OSI Approved :: MIT License
Classifier: Operating System :: OS Independent
Classifier: Framework :: Django
Classifier: Framework :: Django :: 1.11
Classifier: Programming Language :: Python
Classifier: Programming Language :: Python :: 2.7
Classifier: Programming Language :: Python :: 3.6
Classifier: Programming Language :: Python :: 3.7
Classifier: Topic :: Internet :: WWW/HTTP
Classifier: Topic :: Internet :: WWW/HTTP :: Dynamic Content
Requires-Dist: Django (>=1.11)
Requires-Dist: django-cms (>=3.5)
